promptabs/__init__.py
promptabs/__main__.py
promptabs/input_handler.py
promptabs/page.py
promptabs/survey.py
promptabs/terminal.py
promptabs/theme.py
promptabs/types.py
promptabs-0.3.1.dist-info/METADATA
promptabs-0.3.1.dist-info/WHEEL
promptabs-0.3.1.dist-info/entry_points.txt
promptabs-0.3.1.dist-info/top_level.txt
promptabs-0.3.1.dist-info/RECORD
