Metadata-Version: 2.4
Name: promptabs
Version: 0.3.1
Summary: An interactive terminal-based survey/questionnaire module with tab-based navigation
Requires-Python: >=3.10
Requires-Dist: pydantic>=2.12.3
Requires-Dist: readchar>=4.0.0
Requires-Dist: colorama>=0.4.6
Provides-Extra: dev
Requires-Dist: pytest>=7.0; extra == "dev"
Requires-Dist: pytest-cov>=4.0; extra == "dev"
